pyQArk/QArkConfig.py
pyQArk/__init__.py
pyQArk/Core/QArkCriticityLevel.py
pyQArk/Core/QArkDomXml.py
pyQArk/Core/QArkException.py
pyQArk/Core/QArkExceptionHandableObject.py
pyQArk/Core/QArkExceptionHandler.py
pyQArk/Core/QArkFuncArg.py
pyQArk/Core/QArkFunction.py
pyQArk/Core/QArkFunctionFactory.py
pyQArk/Core/QArkFunctor.py
pyQArk/Core/QArkFunctorFactory.py
pyQArk/Core/QArkMessage.py
pyQArk/Core/QArkMessageSender.py
pyQArk/Core/QArkMimeData.py
pyQArk/Core/QArkPlotableObject.py
pyQArk/Core/QArkQt.py
pyQArk/Core/QArkRange.py
pyQArk/Core/QArkUiCompiler.py
pyQArk/Core/QArkUiLoader.py
pyQArk/Core/QArkVectorDataSet.py
pyQArk/Core/QArkWarning.py
pyQArk/Core/QArkWarningSender.py
pyQArk/Core/QArkWorker.py
pyQArk/Core/QArkWorkerController.py
pyQArk/Core/QArkWorkerInterruptor.py
pyQArk/Core/QArkWorkerThread.py
pyQArk/Core/QArkWorkerThreadController.py
pyQArk/Core/QArkWorkerThreadController_EventDriven.py
pyQArk/Core/QArkWorkerThreadController_QThreadSubclassing.py
pyQArk/Core/QArkWorkerThread_QThreadSubclassing.py
pyQArk/Core/QArkWorker_EventDriven.py
pyQArk/Core/QArkWorker_QThreadSubclassing.py
pyQArk/Core/__init__.py
pyQArk/Dialogs/QArkDialog.py
pyQArk/Dialogs/__init__.py
pyQArk/Dialogs/QArkCriticalMessageBox/QArkCriticalMessageBox.py
pyQArk/Dialogs/QArkCriticalMessageBox/__init__.py
pyQArk/Dialogs/QArkExportPlotWidgetDialog/QArkExportPlotWidgetDialog.py
pyQArk/Dialogs/QArkExportPlotWidgetDialog/QArkExportPlotWidgetDialog.ui
pyQArk/Dialogs/QArkExportPlotWidgetDialog/Ui_QArkExportPlotWidgetDialog.py
pyQArk/Dialogs/QArkExportPlotWidgetDialog/__init__.py
pyQArk/Dialogs/QArkInfoWizardDialog/QArkInfoWizardDialog.py
pyQArk/Dialogs/QArkInfoWizardDialog/QArkInfoWizardPage.py
pyQArk/Dialogs/QArkInfoWizardDialog/QArkInfoWizardWelcomePage.py
pyQArk/Dialogs/QArkInfoWizardDialog/__init__.py
pyQArk/Dialogs/QArkMplPlotDialog/QArkMplPlotDialog.py
pyQArk/Dialogs/QArkMplPlotDialog/__init__.py
pyQArk/Dialogs/QArkOpenFilterFileDialog/QArkOpenFilterFileDialog.py
pyQArk-0.3.1.dist-info/LICENSE
pyQArk-0.3.1.dist-info/METADATA
pyQArk-0.3.1.dist-info/WHEEL
pyQArk-0.3.1.dist-info/top_level.txt
pyQArk-0.3.1.dist-info/RECORD
