Metadata-Version: 2.1
Name: pyQArk
Version: 0.3.1
Summary: Python 3 Qt5 framework
Home-page: https://github.com/arnaudkelbert/pyqark
Author: Arnaud Kelbert
Author-email: arnaud.kelbert@gmail.com
License: Apache V2
Keywords: one,two
Platform: any
Classifier: Environment :: X11 Applications :: Qt
Classifier: Programming Language :: Python
Classifier: Programming Language :: Python :: 3
Requires-Python: >=3.8
License-File: LICENSE
Requires-Dist: lxml >=4.9.2
Requires-Dist: PyQt5 >=5.15.9
Requires-Dist: pyqtgraph >=0.13.3
Requires-Dist: requests >=2.31.0
Requires-Dist: pandas >=2.0.3
Requires-Dist: matplotlib >=3.7.1
Requires-Dist: numpy >=1.24.4
